conda_dependency_cleaner/__init__.py
conda_dependency_cleaner/_clean_environment_from_file.py
conda_dependency_cleaner/_convert_pip_to_conda.py
conda_dependency_cleaner/_version.py
conda_dependency_cleaner/cdc.py
conda_dependency_cleaner/utility/__init__.py
conda_dependency_cleaner/utility/_dependency.py
conda_dependency_cleaner/utility/_get_dependeny_graph.py
conda_dependency_cleaner/utility/_logging.py
conda_dependency_cleaner/utility/_to_yaml_patch.py
conda_dependency_cleaner-0.0.3.dist-info/LICENSE
conda_dependency_cleaner-0.0.3.dist-info/METADATA
conda_dependency_cleaner-0.0.3.dist-info/WHEEL
conda_dependency_cleaner-0.0.3.dist-info/entry_points.txt
conda_dependency_cleaner-0.0.3.dist-info/RECORD
