Metadata-Version: 2.3
Name: conda-dependency-cleaner
Version: 0.0.3
Summary: Clean your conda yaml file and convert pip dependencies to conda.
License: MIT
Author: Oliver Weissl
Author-email: weissl@fortiss.org
Classifier: Development Status :: 2 - Pre-Alpha
Classifier: Intended Audience :: Developers
Classifier: License :: OSI Approved :: MIT License
Classifier: Programming Language :: Python :: 2
Classifier: Programming Language :: Python :: 2.7
Classifier: Programming Language :: Python :: 3
Classifier: Programming Language :: Python :: 3.4
Classifier: Programming Language :: Python :: 3.5
Classifier: Programming Language :: Python :: 3.6
Classifier: Programming Language :: Python :: 3.7
Classifier: Programming Language :: Python :: 3.8
Classifier: Programming Language :: Python :: 3.9
Classifier: Programming Language :: Python :: 3.10
Classifier: Programming Language :: Python :: 3.11
Classifier: Programming Language :: Python :: 3.12
Classifier: Programming Language :: Python :: 3.13
Classifier: Topic :: Utilities
Classifier: Typing :: Typed
Requires-Dist: conda (>24.0.0)
Requires-Dist: matplotlib (>=3.0.0,<4.0.0)
Requires-Dist: networkx (>=3.2.1,<4.0.0)
Project-URL: Repository, https://github.com/oliverweissl/CondaDependencyCleaner
